CHANGES.txt
README.txt
setup.cfg
setup.py
src/erp5/__init__.py
src/erp5.utils.dists.egg-info/PKG-INFO
src/erp5.utils.dists.egg-info/SOURCES.txt
src/erp5.utils.dists.egg-info/dependency_links.txt
src/erp5.utils.dists.egg-info/entry_points.txt
src/erp5.utils.dists.egg-info/namespace_packages.txt
src/erp5.utils.dists.egg-info/top_level.txt
src/erp5/utils/__init__.py
src/erp5/utils/dists/__init__.py
src/erp5/utils/dists/bt5.py
src/erp5/utils/dists/genbt5list.py
src/erp5/utils/dists/repository.py