Metadata-Version: 1.0
Name: erp5.utils.dists
Version: 0.0.1dev-r42989
Summary: This library aims to provide utility scripts to manipulate BT5 compress and repositories creation.
Home-page: UNKNOWN
Author: Rafael Monnerat
Author-email: rafael@nexedi.com
License: GPLv3
Keywords: erp5 bt5 distribute
Platform: UNKNOWN
Classifier: Topic :: Utilities
Classifier: Topic :: System :: Archiving :: Packaging
